<?xml version="1.0" encoding="UTF-8"?>
<!DOCTYPE tiles-definitions PUBLIC
       "-//Apache Software Foundation//DTD Tiles Configuration 2.0//EN"
       "http://tiles.apache.org/dtds/tiles-config_2_0.dtd">
<tiles-definitions>
	
    <definition name="base.layout" template="/WEB-INF/jsp/layouts/baseLayout.jsp">
        <put-attribute name="header" value="/WEB-INF/jsp/common/header.jsp"/>
        <put-attribute name="menu" value="/WEB-INF/jsp/common/menu.jsp"/>
        <put-attribute name="footer" value="/WEB-INF/jsp/common/footer.jsp"/>
    </definition>
	
    <!-- Error -->
    <definition name="error" extends="base.layout">
	<put-attribute name="body" value="/WEB-INF/jsp/error.jsp" />
    </definition>
        
    <!-- Home -->
    <definition name="home" extends="base.layout">
        <put-attribute name="body" value="/WEB-INF/jsp/home.jsp" />
    </definition>
	
    <!--  Administracion -->
    <definition name="usuarioSearch" extends="base.layout">
        <put-attribute name="body" value="/WEB-INF/jsp/administracion/usuarioSearch.jsp"/>
    </definition>
    <definition name="usuarioEdit" extends="base.layout">
        <put-attribute name="body" value="/WEB-INF/jsp/administracion/usuarioEdit.jsp"/>
    </definition>
    <definition name="usuarioView" extends="base.layout">
        <put-attribute name="body" value="/WEB-INF/jsp/administracion/usuarioView.jsp"/>
    </definition>
</tiles-definitions>